Single Port Ram/single_port_ram.sv
`timescale 1ns/1ns
module single_port_RAM (
    input [7:0]data_in,
    input [5:0]addr,
    input we,
    input clock,
    output reg [7:0]q
);
    reg [7:0]ram[0:63];
    always @(posedge clock) 
    begin
      if (we) 
      begin
        ram[addr] <= data_in;
      end    
      else
        q <= ram[addr];
    end
endmodule

Single Port Ram/single_port_ram_tb.sv
`timescale 1ns/1ns
`include "single_port_ram.sv"

module single_port_RAM_tb;
reg [7:0]data;
reg [5:0]addr;
reg clock;
reg we;
wire [7:0]q;

single_port_RAM spr1(
    .data_in(data),
    .addr(addr),
    .we(we),
    .clock(clock),
    .q(q));

initial 
begin
  $dumpfile("ram_tb.vcd");
  $dumpvars(1,single_port_RAM_tb);

  clock = 1'b1;
  forever #5 clock = ~clock;    
end

initial 
begin
    data = 8'h01;
    addr = 6'd0;
    we = 1'b1;
    #10;

    data = 8'h02;
    addr = 6'd1;
    #10;

    data = 8'h03;
    addr = 6'd2;
    #10;

    addr = 6'd0;
    we = 1'b0;
    #10;

    addr = 6'd1;
    #10;

    addr = 6'd2;
    #10;

    data = 8'h04;
    addr = 6'd1;
    we = 1'b1;
    #10;

    addr = 6'd1;
    we = 1'b0;
    #10;
end

initial begin
    #80 $finish;
end
endmodule

Single Port Ram/ram_tb.vcd
$date
	Mon Jul 15 15:25:09 2024
$end
$version
	Icarus Verilog
$end
$timescale
	1ns
$end
$scope module single_port_RAM_tb $end
$var wire 8 ! q [7:0] $end
$var reg 6 " addr [5:0] $end
$var reg 1 # clock $end
$var reg 8 $ data [7:0] $end
$var reg 1 % we $end
$upscope $end
$enddefinitions $end
#0
$dumpvars
1%
b1 $
1#
b0 "
bx !
$end
#5
0#
#10
1#
b1 "
b10 $
#15
0#
#20
1#
b10 "
b11 $
#25
0#
#30
b1 !
1#
0%
b0 "
#35
0#
#40
b10 !
1#
b1 "
#45
0#
#50
b11 !
1#
b10 "
#55
0#
#60
1#
1%
b1 "
b100 $
#65
0#
#70
b100 !
1#
0%
